n2d/N2D.py
n2d/__init__.py
n2d/datasets.py
n2d/generators.py
n2d/linear_assignment.py
n2d-0.3.2.dist-info/METADATA
n2d-0.3.2.dist-info/WHEEL
n2d-0.3.2.dist-info/top_level.txt
n2d-0.3.2.dist-info/RECORD
