Metadata-Version: 2.1
Name: n2d
Version: 0.3.2
Summary: (Not too) deep clustering
Home-page: https://github.com/josephsdavid/N2D-OOP
Maintainer: david Josephs
Maintainer-email: josephsd@smu.edu
License: MIT
Platform: UNKNOWN
Classifier: Programming Language :: Python :: 3
Classifier: License :: OSI Approved :: MIT License
Classifier: Operating System :: OS Independent
Requires-Dist: numpy
Requires-Dist: scikit-learn
Requires-Dist: umap-learn
Requires-Dist: tensorflow
Requires-Dist: scipy
Requires-Dist: h5py (>=2.0.0)
Requires-Dist: matplotlib
Requires-Dist: seaborn
Requires-Dist: pandas
